bja_utils/__init__.py
bja_utils/analysis/__init__.py
bja_utils/analysis/cross_ome_correlation.py
bja_utils/analysis/enrichment.py
bja_utils/analysis/pca.py
bja_utils/analysis/stats.py
bja_utils/parsing/__init__.py
bja_utils/parsing/glyco.py
bja_utils/parsing/lipids.py
bja_utils/parsing/parse_uniprot.py
bja_utils/plotly_apps/VolcanoPlot.py
bja_utils/plotly_apps/__init__.py
bja_utils/plotly_apps/utils.py
bja_utils/plotting/BJA_matplotlib_stylesheet.mplstyle
bja_utils/plotting/__init__.py
bja_utils/plotting/plotting.py
bja_utils/processing/__init__.py
bja_utils/processing/impute_data.py
bja_utils/processing/kendall_influence.py
bja_utils/processing/multiprocess_corr.py
bja_utils/resources/GO_term_description_map.json
bja_utils/resources/__init__.py
bja_utils/resources/compound_superclasses.json
bja_utils/resources/fatty_acyls_per_lipid_class.json
bja_utils/resources/molec_class_abbrev.json
bja_utils/utils/__init__.py
bja_utils/utils/test_local_package.py
bja_utils/utils/utils.py
bja_utils-0.1.7.dist-info/METADATA
bja_utils-0.1.7.dist-info/WHEEL
bja_utils-0.1.7.dist-info/top_level.txt
bja_utils-0.1.7.dist-info/RECORD
