Metadata-Version: 2.4
Name: bja_utils
Version: 0.1.7
Summary: Convenience functions for mass spectrometry proteomics & lipidomics analysis, parsing, statisticss, biological interpretation, and plotting.
Author: Benton Anderson
Classifier: Programming Language :: Python :: 3
Classifier: Programming Language :: Python :: 3.10
Classifier: Programming Language :: Python :: 3.11
Classifier: Programming Language :: Python :: 3.12
Classifier: Operating System :: OS Independent
Requires-Python: >=3.9
Requires-Dist: pandas>=1.0.0
Requires-Dist: numpy>=1.20.0
Requires-Dist: matplotlib>=3.5.0
Requires-Dist: seaborn>=0.10.0
Requires-Dist: scipy>=1.11.0
Requires-Dist: statsmodels>=0.11.1
Requires-Dist: goatools>=1.5.1
Provides-Extra: parsing
Requires-Dist: pygoslin; extra == "parsing"
Provides-Extra: plotly-apps
Requires-Dist: plotly>6.0.0; extra == "plotly-apps"
Requires-Dist: dash-ag-grid>=32.3.2; extra == "plotly-apps"
Provides-Extra: all
Requires-Dist: pygoslin; extra == "all"
Requires-Dist: plotly>6.0.0; extra == "all"
Requires-Dist: dash-ag-grid>=32.3.2; extra == "all"
Dynamic: author
Dynamic: classifier
Dynamic: description
Dynamic: description-content-type
Dynamic: provides-extra
Dynamic: requires-dist
Dynamic: requires-python
Dynamic: summary
